alibabacloud_cr20181201/__init__.py
alibabacloud_cr20181201/client.py
alibabacloud_cr20181201/models/__init__.py
alibabacloud_cr20181201/models/_artifact_lifecycle_policy.py
alibabacloud_cr20181201/models/_cancel_artifact_build_task_request.py
alibabacloud_cr20181201/models/_cancel_artifact_build_task_response.py
alibabacloud_cr20181201/models/_cancel_artifact_build_task_response_body.py
alibabacloud_cr20181201/models/_cancel_repo_build_record_request.py
alibabacloud_cr20181201/models/_cancel_repo_build_record_response.py
alibabacloud_cr20181201/models/_cancel_repo_build_record_response_body.py
alibabacloud_cr20181201/models/_cancel_repo_sync_task_request.py
alibabacloud_cr20181201/models/_cancel_repo_sync_task_response.py
alibabacloud_cr20181201/models/_cancel_repo_sync_task_response_body.py
alibabacloud_cr20181201/models/_change_resource_group_request.py
alibabacloud_cr20181201/models/_change_resource_group_response.py
alibabacloud_cr20181201/models/_change_resource_group_response_body.py
alibabacloud_cr20181201/models/_create_artifact_build_rule_request.py
alibabacloud_cr20181201/models/_create_artifact_build_rule_response.py
alibabacloud_cr20181201/models/_create_artifact_build_rule_response_body.py
alibabacloud_cr20181201/models/_create_artifact_build_rule_shrink_request.py
alibabacloud_cr20181201/models/_create_artifact_lifecycle_rule_request.py
alibabacloud_cr20181201/models/_create_artifact_lifecycle_rule_response.py
alibabacloud_cr20181201/models/_create_artifact_lifecycle_rule_response_body.py
alibabacloud_cr20181201/models/_create_artifact_subscription_rule_request.py
alibabacloud_cr20181201/models/_create_artifact_subscription_rule_response.py
alibabacloud_cr20181201/models/_create_artifact_subscription_rule_response_body.py
alibabacloud_cr20181201/models/_create_artifact_subscription_task_request.py
alibabacloud_cr20181201/models/_create_artifact_subscription_task_response.py
alibabacloud_cr20181201-2.1.1.dist-info/LICENSE
alibabacloud_cr20181201-2.1.1.dist-info/METADATA
alibabacloud_cr20181201-2.1.1.dist-info/WHEEL
alibabacloud_cr20181201-2.1.1.dist-info/top_level.txt
alibabacloud_cr20181201-2.1.1.dist-info/RECORD
